arsodeco/__init__.py
arsodeco-0.0.1.dist-info/METADATA
arsodeco-0.0.1.dist-info/WHEEL
arsodeco-0.0.1.dist-info/top_level.txt
arsodeco-0.0.1.dist-info/RECORD
