Metadata-Version: 2.1
Name: arsodeco
Version: 0.0.1
Summary: Decorators Pack
Home-page: UNKNOWN
License: UNKNOWN
Platform: UNKNOWN
